oriel_cornerstone_260/__init__.py
oriel_cornerstone_260/_version.py
oriel_cornerstone_260/monochromator.py
oriel_cornerstone_260-0.1.0.post1.dist-info/LICENSE
oriel_cornerstone_260-0.1.0.post1.dist-info/METADATA
oriel_cornerstone_260-0.1.0.post1.dist-info/WHEEL
oriel_cornerstone_260-0.1.0.post1.dist-info/top_level.txt
oriel_cornerstone_260-0.1.0.post1.dist-info/RECORD
