Metadata-Version: 2.1
Name: oriel-cornerstone-260
Version: 0.1.0.post1
Summary: Controller class for communicating with an Oriel Cornerstone 260 monochromator.
Home-page: UNKNOWN
Author: Brian Carlsen
Author-email: carlsen.bri@gmail.com
License: UNKNOWN
Project-URL: Source Code, https://github.com/bicarlsen/oriel-cornerstone-260
Project-URL: Bug Tracker, https://github.com/bicarlsen/oriel-cornerstone-260/issues
Keywords: oriel,cornerstone,newport,monochromator
Platform: UNKNOWN
Classifier: Programming Language :: Python :: 3
Classifier: License :: OSI Approved :: GNU Lesser General Public License v3 or later (LGPLv3+)
Classifier: Operating System :: OS Independent
Classifier: Development Status :: 3 - Alpha
License-File: LICENSE
Requires-Dist: pyserial
